showroom_recorder/__init__.py
showroom_recorder/__main__.py
showroom_recorder/common.py
showroom_recorder/version.py
showroom_recorder/processor/__init__.py
showroom_recorder/processor/uploader.py
showroom_recorder/processor/video.py
showroom_recorder/utils/__init__.py
showroom_recorder/utils/load_config.py
showroom_recorder-0.7.15.dist-info/licenses/LICENSE
showroom_recorder-0.7.15.dist-info/METADATA
showroom_recorder-0.7.15.dist-info/WHEEL
showroom_recorder-0.7.15.dist-info/entry_points.txt
showroom_recorder-0.7.15.dist-info/top_level.txt
showroom_recorder-0.7.15.dist-info/zip-safe
showroom_recorder-0.7.15.dist-info/RECORD
