Metadata-Version: 2.4
Name: showroom-recorder
Version: 0.7.15
Summary: Recording Showroom Streaming Video
Home-page: https://github.com/vacabun/showroom-recorder
Author: vacabun
Author-email: maguotong66@gmail.com
Keywords: video download showroom
Platform: any
License-File: LICENSE
Requires-Dist: pytz
Requires-Dist: requests
Requires-Dist: ffmpeg-python
Requires-Dist: webdav4
Requires-Dist: biliup
Requires-Dist: m3u8
Dynamic: author
Dynamic: author-email
Dynamic: description
Dynamic: description-content-type
Dynamic: home-page
Dynamic: keywords
Dynamic: license-file
Dynamic: platform
Dynamic: requires-dist
Dynamic: summary
